{
  "results": [
    {
      "id": 11,
      "title": "Vitamin A Gummies",
      "image": "assets/restaurants/vitamina2.jpg",
      "imageType": "jpg"
    },
    {
      "id": 12,
      "title": "Vitamin A Liquid",
      "image": "assets/restaurants/vitamina3.jpg",
      "imageType": "jpg"
    },
    {
      "id": 13,
      "title": "Vitamin A Capsules",
      "image": "assets/restaurants/vitamina4.jpg",
      "imageType": "jpg"
    },
    {
      "id": 14,
      "title": "Vitamin A Drops",
      "image": "assets/restaurants/vitamina5.png",
      "imageType": "png"
    },
    {
      "id": 15,
      "title": "Vitamin B Complex",
      "image": "assets/restaurants/vitaminb.jpg",
      "imageType": "jpg"
    },
    {
      "id": 16,
      "title": "Vitamin B1",
      "image": "assets/restaurants/vitaminb1.png",
      "imageType": "png"
    },
    {
      "id": 17,
      "title": "Vitamin B2",
      "image": "assets/restaurants/vitaminb2.jpg",
      "imageType": "jpg"
    },
    {
      "id": 18,
      "title": "Vitamin B3",
      "image": "assets/restaurants/vitaminb3.jpg",
      "imageType": "jpg"
    },
    {
      "id": 19,
      "title": "Vitamin B6",
      "image": "assets/restaurants/vitaminb6.jpg",
      "imageType": "jpg"
    },
    {
      "id": 20,
      "title": "Vitamin B12",
      "image": "assets/restaurants/vitaminb12.jpg",
      "imageType": "jpg"
    }
  ],
  "offset": 0,
  "number": 10,
  "totalResults": 10
}